{
  "langs": ["en"],

  "loadingError": {
    "en": "An error occured: {0}"
  },

  "root": {
    "en": "root"
  },

  "newFolder": {
    "en": "New Folder"
  },

  "newDocument": {
    "en": "New Document"
  },

  "newProjectSpace": {
    "en": "New Project Space"
  },

  "folder": {
    "en": "folder"
  },

  "projectSpace": {
    "en": "project space"
  },

  "image": {
    "en": "image"
  },

  "video": {
    "en": "video"
  },

  "audio": {
    "en": "audio"
  },

  "children": {
    "en": "Children: {0}"
  },

  "versions": {
    "en": "Versions: {0}"
  }

}